async_lru_cache/__init__.py
async_lru_cache/cache.py
async_lru_cache-0.2.0.dist-info/METADATA
async_lru_cache-0.2.0.dist-info/WHEEL
async_lru_cache-0.2.0.dist-info/licenses/LICENSE
async_lru_cache-0.2.0.dist-info/RECORD
