Metadata-Version: 2.4
Name: async-lru-cache
Version: 0.2.0
Summary: A fully asynchronous LRU cache decorator
Project-URL: Homepage, https://github.com/AetherMagee/async-lru-cache
Project-URL: Repository, https://github.com/AetherMagee/async-lru-cache.git
Project-URL: Issues, https://github.com/AetherMagee/async-lru-cache/issues
Author-email: Aether <aether@pierdoling.org>
License-File: LICENSE
Keywords: async,asyncio,cache,decorator,lru
Classifier: Development Status :: 4 - Beta
Classifier: Intended Audience :: Developers
Classifier: License :: OSI Approved :: MIT License
Classifier: Programming Language :: Python :: 3
Classifier: Programming Language :: Python :: 3.9
Classifier: Programming Language :: Python :: 3.10
Classifier: Programming Language :: Python :: 3.11
Classifier: Programming Language :: Python :: 3.12
Classifier: Topic :: Software Development :: Libraries :: Python Modules
Requires-Python: >=3.9
